README.md
pyproject.toml
setup.py
management/__init__.py
management/cli.py
management/cluster_ops.py
management/cnode_client.py
management/compute_node_ops.py
management/constants.py
management/distr_controller.py
management/kv_store.py
management/mgmt_node_ops.py
management/pci_utils.py
management/rpc_client.py
management/shell_utils.py
management/snode_client.py
management/storage_node_ops.py
management/utils.py
management/controllers/__init__.py
management/controllers/caching_node_controller.py
management/controllers/cluster_events.py
management/controllers/cluster_lifecycle.py
management/controllers/device_lifecycle.py
management/controllers/events_controller.py
management/controllers/health_controller.py
management/controllers/lvol_controller.py
management/controllers/mgmt_events.py
management/controllers/node_lifecycle.py
management/controllers/pool_controller.py
management/controllers/snapshot_controller.py
management/controllers/stats_controller.py
management/controllers/storage_events.py
management/models/__init__.py
management/models/base_model.py
management/models/caching_node.py
management/models/cluster.py
management/models/compute_node.py
management/models/device_stat.py
management/models/events.py
management/models/global_settings.py
management/models/iface.py
management/models/lvol_model.py
management/models/mgmt_node.py
management/models/nvme_device.py
management/models/pool.py
management/models/snapshot.py
management/models/stats.py
management/models/storage_node.py
management/scripts/__init__.py
management/scripts/clean_local_storage_deploy.sh
management/scripts/config_docker.sh
management/scripts/db_config_double.sh
management/scripts/db_config_single.sh
management/scripts/deploy_stack.sh
management/scripts/docker-compose-swarm.yml
management/scripts/haproxy.cfg
management/scripts/install_deps.sh
management/scripts/run_ssh.sh
management/scripts/set_db_config.sh
management/scripts/stack_deploy_wait.sh
management/services/__init__.py
sbcli.egg-info/PKG-INFO
sbcli.egg-info/SOURCES.txt
sbcli.egg-info/dependency_links.txt
sbcli.egg-info/entry_points.txt
sbcli.egg-info/requires.txt
sbcli.egg-info/top_level.txt