Metadata-Version: 2.1
Name: sbcli
Version: 4.5.4
Summary: CLI for managing SimplyBlock cluster
Home-page: https://github.com/
Author: Hamdy Khader
Author-email: hamdy.khader@gmail.com
Requires-Dist: foundationdb
Requires-Dist: requests
Requires-Dist: typing
Requires-Dist: prettytable
Requires-Dist: docker
Requires-Dist: psutil
Requires-Dist: py-cpuinfo
